<?xml version="1.0" encoding="UTF-8" ?>
<!DOCTYPE mapper PUBLIC "-//mybatis.org//DTD Mapper 3.0//EN" "http://mybatis.org/dtd/mybatis-3-mapper.dtd" >
<mapper namespace="com.s1.common.accounts.loan.mapper.AccountCommitmentMapper" >
  <resultMap id="BaseResultMap" type="com.s1.common.accounts.loan.dao.AccountCommitment" >
    <!--
      WARNING - @mbggenerated
      This element is automatically generated by MyBatis Generator, do not modify.
      This element was generated on Tue Dec 10 10:57:42 IST 2013.
    -->
    <id column="BNKCOMMITMENTKY" property="oid" jdbcType="INTEGER" typeHandler="com.s1.arch.ibatis.ObjectIdTypeHandler" />
    <result column="BNKACCTKY" property="bnkAcctOid" jdbcType="INTEGER" typeHandler="com.s1.arch.ibatis.ObjectIdTypeHandler" />
    <result column="COMMITMENT" property="commitment" jdbcType="VARCHAR" />
    <result column="UPDATEDTTM" property="updateDateTime" jdbcType="TIMESTAMP" />
    <result column="UPDATEUSER" property="updateUser" jdbcType="VARCHAR" />
    <result column="VERSIONSTAMP" property="versionStamp" jdbcType="SMALLINT" />
    <result column="SOAUIID" property="soaUIID" jdbcType="VARCHAR" />
  </resultMap>
  
  <!--This is added for getting Notes that are child of some Sub-Commitment-->
  <resultMap id="childNotesMap" type="com.s1.common.accounts.loan.dao.AccountNotes" >
    <id column="BNKACCTNOTEKY" property="oid" jdbcType="INTEGER" typeHandler="com.s1.arch.ibatis.ObjectIdTypeHandler" />
    <result column="NOTE_ACCTKY" property="bnkAcctOid" jdbcType="INTEGER" typeHandler="com.s1.arch.ibatis.ObjectIdTypeHandler" />
    <result column="NOTE_COMMITMENTKY" property="commitmentOid" jdbcType="INTEGER" typeHandler="com.s1.arch.ibatis.ObjectIdTypeHandler" />
    <result column="NOTE_SUBCOMMITMENTKY" property="subCommitmentOid" jdbcType="INTEGER" typeHandler="com.s1.arch.ibatis.ObjectIdTypeHandler" />
    <result column="NOTE" property="note" jdbcType="VARCHAR" />
    <result column="NOTE_UPDATEDTTM" property="updateDateTime" jdbcType="TIMESTAMP" />
    <result column="NOTE_UPDATEUSER" property="updateUser" jdbcType="VARCHAR" />
    <result column="NOTE_VERSIONSTAMP" property="versionStamp" jdbcType="SMALLINT" />
  </resultMap>
  
  <resultMap id="subCommitmentNoteView" extends="BaseResultMap" type="com.s1.common.accounts.loan.dao.AccountSubCommitment">    
	<id column="BNKSUBCOMMITMENTKY" property="objectId" jdbcType="INTEGER" typeHandler="com.s1.arch.ibatis.ObjectIdTypeHandler" />
	<collection property="subCommitmentNoteList" column="BNKSUBCOMMITMENTKY" javaType="ArrayList" ofType="com.s1.common.accounts.loan.dao.AccountNotes" resultMap="childNotesMap"/>	
  </resultMap>
  
  <select id="getSubCommitmentDataByCommitmentOid"  parameterType="com.s1.arch.utilities.ObjectId"  resultMap="subCommitmentNoteView"> 
  SELECT 
	BSC.BNKSUBCOMMITMENTKY,
	BSC.BNKCOMMITMENTKY,
	BSC.BNKACCTKY,
	BSC.SUBCOMMITMENT,
	BSC.UPDATEDTTM,
	BSC.UPDATEUSER,
	BSC.VERSIONSTAMP,
	BAN.BNKACCTNOTEKY,
	BAN.BNKACCTKY NOTE_ACCTKY,
	BAN.BNKCOMMITMENTKY NOTE_COMMITMENTKY,
	BAN.BNKSUBCOMMITMENTKY NOTE_SUBCOMMITMENTKY,
	BAN.NOTE,
	BAN.UPDATEDTTM NOTE_UPDATEDTTM,
	BAN.UPDATEUSER NOTE_UPDATEUSER,
	BAN.VERSIONSTAMP NOTE_VERSIONSTAMP
	FROM BNKSUBCOMMITMENT AS BSC LEFT OUTER JOIN BNKACCTNOTE AS BAN
	ON BSC.BNKSUBCOMMITMENTKY = BAN.BNKSUBCOMMITMENTKY
	WHERE BSC.BNKCOMMITMENTKY = #{commitmentOid,jdbcType=INTEGER,typeHandler=com.s1.arch.ibatis.ObjectIdTypeHandler}
  </select>
  
  
  <sql id="Example_Where_Clause" >
    <!--
      WARNING - @mbggenerated
      This element is automatically generated by MyBatis Generator, do not modify.
      This element was generated on Tue Dec 10 10:57:42 IST 2013.
    -->
    <where >
      <foreach collection="oredCriteria" item="criteria" separator="or" >
        <if test="criteria.valid" >
          <trim prefix="(" suffix=")" prefixOverrides="and" >
            <foreach collection="criteria.criteria" item="criterion" >
              <choose >
                <when test="criterion.noValue" >
                  and ${criterion.condition}
                </when>
                <when test="criterion.singleValue" >
                  and ${criterion.condition} #{criterion.value}
                </when>
                <when test="criterion.betweenValue" >
                  and ${criterion.condition} #{criterion.value} and #{criterion.secondValue}
                </when>
                <when test="criterion.listValue" >
                  and ${criterion.condition}
                  <foreach collection="criterion.value" item="listItem" open="(" close=")" separator="," >
                    #{listItem}
                  </foreach>
                </when>
              </choose>
            </foreach>
            <foreach collection="criteria.oidCriteria" item="criterion" >
              <choose >
                <when test="criterion.noValue" >
                  and ${criterion.condition}
                </when>
                <when test="criterion.singleValue" >
                  and ${criterion.condition} #{criterion.value,typeHandler=com.s1.arch.ibatis.ObjectIdTypeHandler}
                </when>
                <when test="criterion.betweenValue" >
                  and ${criterion.condition} #{criterion.value,typeHandler=com.s1.arch.ibatis.ObjectIdTypeHandler} and #{criterion.secondValue,typeHandler=com.s1.arch.ibatis.ObjectIdTypeHandler}
                </when>
                <when test="criterion.listValue" >
                  and ${criterion.condition}
                  <foreach collection="criterion.value" item="listItem" open="(" close=")" separator="," >
                    #{listItem,typeHandler=com.s1.arch.ibatis.ObjectIdTypeHandler}
                  </foreach>
                </when>
              </choose>
            </foreach>
            <foreach collection="criteria.bnkAcctOidCriteria" item="criterion" >
              <choose >
                <when test="criterion.noValue" >
                  and ${criterion.condition}
                </when>
                <when test="criterion.singleValue" >
                  and ${criterion.condition} #{criterion.value,typeHandler=com.s1.arch.ibatis.ObjectIdTypeHandler}
                </when>
                <when test="criterion.betweenValue" >
                  and ${criterion.condition} #{criterion.value,typeHandler=com.s1.arch.ibatis.ObjectIdTypeHandler} and #{criterion.secondValue,typeHandler=com.s1.arch.ibatis.ObjectIdTypeHandler}
                </when>
                <when test="criterion.listValue" >
                  and ${criterion.condition}
                  <foreach collection="criterion.value" item="listItem" open="(" close=")" separator="," >
                    #{listItem,typeHandler=com.s1.arch.ibatis.ObjectIdTypeHandler}
                  </foreach>
                </when>
              </choose>
            </foreach>
          </trim>
        </if>
      </foreach>
    </where>
  </sql>
  <sql id="Update_By_Example_Where_Clause" >
    <!--
      WARNING - @mbggenerated
      This element is automatically generated by MyBatis Generator, do not modify.
      This element was generated on Tue Dec 10 10:57:42 IST 2013.
    -->
    <where >
      <foreach collection="example.oredCriteria" item="criteria" separator="or" >
        <if test="criteria.valid" >
          <trim prefix="(" suffix=")" prefixOverrides="and" >
            <foreach collection="criteria.criteria" item="criterion" >
              <choose >
                <when test="criterion.noValue" >
                  and ${criterion.condition}
                </when>
                <when test="criterion.singleValue" >
                  and ${criterion.condition} #{criterion.value}
                </when>
                <when test="criterion.betweenValue" >
                  and ${criterion.condition} #{criterion.value} and #{criterion.secondValue}
                </when>
                <when test="criterion.listValue" >
                  and ${criterion.condition}
                  <foreach collection="criterion.value" item="listItem" open="(" close=")" separator="," >
                    #{listItem}
                  </foreach>
                </when>
              </choose>
            </foreach>
            <foreach collection="criteria.oidCriteria" item="criterion" >
              <choose >
                <when test="criterion.noValue" >
                  and ${criterion.condition}
                </when>
                <when test="criterion.singleValue" >
                  and ${criterion.condition} #{criterion.value,typeHandler=com.s1.arch.ibatis.ObjectIdTypeHandler}
                </when>
                <when test="criterion.betweenValue" >
                  and ${criterion.condition} #{criterion.value,typeHandler=com.s1.arch.ibatis.ObjectIdTypeHandler} and #{criterion.secondValue,typeHandler=com.s1.arch.ibatis.ObjectIdTypeHandler}
                </when>
                <when test="criterion.listValue" >
                  and ${criterion.condition}
                  <foreach collection="criterion.value" item="listItem" open="(" close=")" separator="," >
                    #{listItem,typeHandler=com.s1.arch.ibatis.ObjectIdTypeHandler}
                  </foreach>
                </when>
              </choose>
            </foreach>
            <foreach collection="criteria.bnkAcctOidCriteria" item="criterion" >
              <choose >
                <when test="criterion.noValue" >
                  and ${criterion.condition}
                </when>
                <when test="criterion.singleValue" >
                  and ${criterion.condition} #{criterion.value,typeHandler=com.s1.arch.ibatis.ObjectIdTypeHandler}
                </when>
                <when test="criterion.betweenValue" >
                  and ${criterion.condition} #{criterion.value,typeHandler=com.s1.arch.ibatis.ObjectIdTypeHandler} and #{criterion.secondValue,typeHandler=com.s1.arch.ibatis.ObjectIdTypeHandler}
                </when>
                <when test="criterion.listValue" >
                  and ${criterion.condition}
                  <foreach collection="criterion.value" item="listItem" open="(" close=")" separator="," >
                    #{listItem,typeHandler=com.s1.arch.ibatis.ObjectIdTypeHandler}
                  </foreach>
                </when>
              </choose>
            </foreach>
          </trim>
        </if>
      </foreach>
    </where>
  </sql>
  <sql id="Base_Column_List" >
    <!--
      WARNING - @mbggenerated
      This element is automatically generated by MyBatis Generator, do not modify.
      This element was generated on Tue Dec 10 10:57:42 IST 2013.
    -->
    BNKCOMMITMENTKY, BNKACCTKY, COMMITMENT, UPDATEDTTM, UPDATEUSER, VERSIONSTAMP, SOAUIID
  </sql>
  <select id="selectByExample" resultMap="BaseResultMap" parameterType="com.s1.common.accounts.loan.dao.AccountCommitmentExample" >
    <!--
      WARNING - @mbggenerated
      This element is automatically generated by MyBatis Generator, do not modify.
      This element was generated on Tue Dec 10 10:57:42 IST 2013.
    -->
    select
    <if test="distinct" >
      distinct
    </if>
    <include refid="Base_Column_List" />
    from BNKCOMMITMENT
    <if test="_parameter != null" >
      <include refid="Example_Where_Clause" />
    </if>
    <if test="orderByClause != null" >
      order by ${orderByClause}
    </if>
  </select>
  <select id="selectByPrimaryKey" resultMap="BaseResultMap" parameterType="com.s1.arch.utilities.ObjectId" >
    <!--
      WARNING - @mbggenerated
      This element is automatically generated by MyBatis Generator, do not modify.
      This element was generated on Tue Dec 10 10:57:42 IST 2013.
    -->
    select 
    <include refid="Base_Column_List" />
    from BNKCOMMITMENT
    where BNKCOMMITMENTKY = #{oid,jdbcType=INTEGER,typeHandler=com.s1.arch.ibatis.ObjectIdTypeHandler}
  </select>
  
  <select id="getCommitmentsByAccountOid" resultMap="BaseResultMap" parameterType="com.s1.arch.utilities.ObjectId" >
   
    select
    
    <include refid="Base_Column_List" />
    
    from BNKCOMMITMENT
    where BNKACCTKY = #{accountOid,jdbcType=INTEGER,typeHandler=com.s1.arch.ibatis.ObjectIdTypeHandler}
  </select>
  
  <delete id="deleteByPrimaryKey" parameterType="com.s1.arch.utilities.ObjectId" >
    <!--
      WARNING - @mbggenerated
      This element is automatically generated by MyBatis Generator, do not modify.
      This element was generated on Tue Dec 10 10:57:42 IST 2013.
    -->
    delete from BNKCOMMITMENT
    where BNKCOMMITMENTKY = #{oid,jdbcType=INTEGER,typeHandler=com.s1.arch.ibatis.ObjectIdTypeHandler}
  </delete>
  <delete id="deleteByExample" parameterType="com.s1.common.accounts.loan.dao.AccountCommitmentExample" >
    <!--
      WARNING - @mbggenerated
      This element is automatically generated by MyBatis Generator, do not modify.
      This element was generated on Tue Dec 10 10:57:42 IST 2013.
    -->
    delete from BNKCOMMITMENT
    <if test="_parameter != null" >
      <include refid="Example_Where_Clause" />
    </if>
  </delete>
  <insert id="insert" parameterType="com.s1.common.accounts.loan.dao.AccountCommitment" >
    <!--
      WARNING - @mbggenerated
      This element is automatically generated by MyBatis Generator, do not modify.
      This element was generated on Tue Dec 10 10:57:42 IST 2013.
    -->
    insert into BNKCOMMITMENT (BNKCOMMITMENTKY, 
      BNKACCTKY, 
      COMMITMENT, UPDATEDTTM, UPDATEUSER, 
      VERSIONSTAMP, SOAUIID)
    values (#{oid,jdbcType=INTEGER,typeHandler=com.s1.arch.ibatis.ObjectIdTypeHandler}, 
      #{bnkAcctOid,jdbcType=INTEGER,typeHandler=com.s1.arch.ibatis.ObjectIdTypeHandler}, 
      #{commitment,jdbcType=VARCHAR}, #{updateDateTime,jdbcType=TIMESTAMP}, #{updateUser,jdbcType=VARCHAR}, 
      #{versionStamp,jdbcType=SMALLINT}, #{soaUIID,jdbcType=VARCHAR})
  </insert>
  <insert id="insertSelective" parameterType="com.s1.common.accounts.loan.dao.AccountCommitment" >
    <!--
      WARNING - @mbggenerated
      This element is automatically generated by MyBatis Generator, do not modify.
      This element was generated on Tue Dec 10 10:57:42 IST 2013.
    -->
    insert into BNKCOMMITMENT
    <trim prefix="(" suffix=")" suffixOverrides="," >
      <if test="oid != null" >
        BNKCOMMITMENTKY,
      </if>
      <if test="bnkAcctOid != null" >
        BNKACCTKY,
      </if>
      <if test="commitment != null" >
        COMMITMENT,
      </if>
      <if test="updateDateTime != null" >
        UPDATEDTTM,
      </if>
      <if test="updateUser != null" >
        UPDATEUSER,
      </if>
      <if test="versionStamp != null" >
        VERSIONSTAMP,
      </if>
      <if test="soaUIID != null" >
        SOAUIID,
      </if>
    </trim>
    <trim prefix="values (" suffix=")" suffixOverrides="," >
      <if test="oid != null" >
        #{oid,jdbcType=INTEGER,typeHandler=com.s1.arch.ibatis.ObjectIdTypeHandler},
      </if>
      <if test="bnkAcctOid != null" >
        #{bnkAcctOid,jdbcType=INTEGER,typeHandler=com.s1.arch.ibatis.ObjectIdTypeHandler},
      </if>
      <if test="commitment != null" >
        #{commitment,jdbcType=VARCHAR},
      </if>
      <if test="updateDateTime != null" >
        #{updateDateTime,jdbcType=TIMESTAMP},
      </if>
      <if test="updateUser != null" >
        #{updateUser,jdbcType=VARCHAR},
      </if>
      <if test="versionStamp != null" >
        #{versionStamp,jdbcType=SMALLINT},
      </if>
      <if test="soaUIID != null" >
        #{soaUIID,jdbcType=VARCHAR},
      </if>
    </trim>
  </insert>
  <select id="countByExample" parameterType="com.s1.common.accounts.loan.dao.AccountCommitmentExample" resultType="java.lang.Integer" >
    <!--
      WARNING - @mbggenerated
      This element is automatically generated by MyBatis Generator, do not modify.
      This element was generated on Tue Dec 10 10:57:42 IST 2013.
    -->
    select count(*) from BNKCOMMITMENT
    <if test="_parameter != null" >
      <include refid="Example_Where_Clause" />
    </if>
  </select>
  <update id="updateByExampleSelective" parameterType="map" >
    <!--
      WARNING - @mbggenerated
      This element is automatically generated by MyBatis Generator, do not modify.
      This element was generated on Tue Dec 10 10:57:42 IST 2013.
    -->
    update BNKCOMMITMENT
    <set >
      <if test="record.oid != null" >
        BNKCOMMITMENTKY = #{record.oid,jdbcType=INTEGER,typeHandler=com.s1.arch.ibatis.ObjectIdTypeHandler},
      </if>
      <if test="record.bnkAcctOid != null" >
        BNKACCTKY = #{record.bnkAcctOid,jdbcType=INTEGER,typeHandler=com.s1.arch.ibatis.ObjectIdTypeHandler},
      </if>
      <if test="record.commitment != null" >
        COMMITMENT = #{record.commitment,jdbcType=VARCHAR},
      </if>
      <if test="record.updateDateTime != null" >
        UPDATEDTTM = #{record.updateDateTime,jdbcType=TIMESTAMP},
      </if>
      <if test="record.updateUser != null" >
        UPDATEUSER = #{record.updateUser,jdbcType=VARCHAR},
      </if>
      <if test="record.versionStamp != null" >
        VERSIONSTAMP = #{record.versionStamp,jdbcType=SMALLINT},
      </if>
      <if test="record.soaUIID != null" >
        SOAUIID = #{record.soaUIID,jdbcType=VARCHAR},
      </if>
    </set>
    <if test="_parameter != null" >
      <include refid="Update_By_Example_Where_Clause" />
    </if>
  </update>
  <update id="updateByExample" parameterType="map" >
    <!--
      WARNING - @mbggenerated
      This element is automatically generated by MyBatis Generator, do not modify.
      This element was generated on Tue Dec 10 10:57:42 IST 2013.
    -->
    update BNKCOMMITMENT
    set BNKCOMMITMENTKY = #{record.oid,jdbcType=INTEGER,typeHandler=com.s1.arch.ibatis.ObjectIdTypeHandler},
      BNKACCTKY = #{record.bnkAcctOid,jdbcType=INTEGER,typeHandler=com.s1.arch.ibatis.ObjectIdTypeHandler},
      COMMITMENT = #{record.commitment,jdbcType=VARCHAR},
      UPDATEDTTM = #{record.updateDateTime,jdbcType=TIMESTAMP},
      UPDATEUSER = #{record.updateUser,jdbcType=VARCHAR},
      VERSIONSTAMP = #{record.versionStamp,jdbcType=SMALLINT},
      SOAUIID = #{record.SOAUIID,jdbcType=VARCHAR}
    <if test="_parameter != null" >
      <include refid="Update_By_Example_Where_Clause" />
    </if>
  </update>
  <update id="updateByPrimaryKeySelective" parameterType="com.s1.common.accounts.loan.dao.AccountCommitment" >
    <!--
      WARNING - @mbggenerated
      This element is automatically generated by MyBatis Generator, do not modify.
      This element was generated on Tue Dec 10 10:57:42 IST 2013.
    -->
    update BNKCOMMITMENT
    <set >
      <if test="bnkAcctOid != null" >
        BNKACCTKY = #{bnkAcctOid,jdbcType=INTEGER,typeHandler=com.s1.arch.ibatis.ObjectIdTypeHandler},
      </if>
      <if test="commitment != null" >
        COMMITMENT = #{commitment,jdbcType=VARCHAR},
      </if>
      <if test="updateDateTime != null" >
        UPDATEDTTM = #{updateDateTime,jdbcType=TIMESTAMP},
      </if>
      <if test="updateUser != null" >
        UPDATEUSER = #{updateUser,jdbcType=VARCHAR},
      </if>
      <if test="versionStamp != null" >
        VERSIONSTAMP = #{versionStamp,jdbcType=SMALLINT},
      </if>
      <if test="soaUIID != null" >
        SOAUIID = #{soaUIID,jdbcType=VARCHAR},
      </if>
    </set>
    where BNKCOMMITMENTKY = #{oid,jdbcType=INTEGER,typeHandler=com.s1.arch.ibatis.ObjectIdTypeHandler}
  </update>
  <update id="updateByPrimaryKey" parameterType="com.s1.common.accounts.loan.dao.AccountCommitment" >
    <!--
      WARNING - @mbggenerated
      This element is automatically generated by MyBatis Generator, do not modify.
      This element was generated on Tue Dec 10 10:57:42 IST 2013.
    -->
    update BNKCOMMITMENT
    set BNKACCTKY = #{bnkAcctOid,jdbcType=INTEGER,typeHandler=com.s1.arch.ibatis.ObjectIdTypeHandler},
      COMMITMENT = #{commitment,jdbcType=VARCHAR},
      UPDATEDTTM = #{updateDateTime,jdbcType=TIMESTAMP},
      UPDATEUSER = #{updateUser,jdbcType=VARCHAR},
      VERSIONSTAMP = #{versionStamp,jdbcType=SMALLINT},
      SOAUIID = #{soaUIID,jdbcType=VARCHAR}
    where BNKCOMMITMENTKY = #{oid,jdbcType=INTEGER,typeHandler=com.s1.arch.ibatis.ObjectIdTypeHandler}
  </update>
</mapper>